WarThunder/__init__.py
WarThunder/acmi.py
WarThunder/general.py
WarThunder/mapinfo.py
WarThunder/maps.py
WarThunder/telemetry.py
WarThunder-2.3.4.dist-info/METADATA
WarThunder-2.3.4.dist-info/WHEEL
WarThunder-2.3.4.dist-info/top_level.txt
WarThunder-2.3.4.dist-info/RECORD
