Metadata-Version: 2.1
Name: WarThunder
Version: 2.3.4
Summary: Python package used to access air vehicle telemetry while in War Thunder air battles
Home-page: https://github.com/PowerBroker2/WarThunder
Download-URL: https://github.com/PowerBroker2/WarThunder/archive/2.3.4.tar.gz
Author: Power_Broker
Author-email: gitstuff2@gmail.com
Keywords: War Thunder
Requires-Dist: imagehash
Requires-Dist: requests
Requires-Dist: Pillow
Requires-Dist: simplejson
